LICENSE
README.md
setup.py
i18n/__init__.py
i18n.lang.egg-info/PKG-INFO
i18n.lang.egg-info/SOURCES.txt
i18n.lang.egg-info/dependency_links.txt
i18n.lang.egg-info/entry_points.txt
i18n.lang.egg-info/requires.txt
i18n.lang.egg-info/top_level.txt
i18n/_vendors/__init__.py
i18n/_vendors/loguru/__init__.py
i18n/_vendors/loguru/_better_exceptions.py
i18n/_vendors/loguru/_colorama.py
i18n/_vendors/loguru/_colorizer.py
i18n/_vendors/loguru/_ctime_functions.py
i18n/_vendors/loguru/_datetime.py
i18n/_vendors/loguru/_defaults.py
i18n/_vendors/loguru/_error_interceptor.py
i18n/_vendors/loguru/_file_sink.py
i18n/_vendors/loguru/_filters.py
i18n/_vendors/loguru/_get_frame.py
i18n/_vendors/loguru/_handler.py
i18n/_vendors/loguru/_locks_machinery.py
i18n/_vendors/loguru/_logger.py
i18n/_vendors/loguru/_recattrs.py
i18n/_vendors/loguru/_simple_sinks.py
i18n/_vendors/loguru/_string_parsers.py
i18n/lang/__init__.py
i18n/lang/__main__.py
i18n/lang/_i18n.py
i18n/lang/_sidle.py
i18n/lang/cli.py
i18n/lang/constants.py
i18n/lang/errors.py
i18n/lang/logs.py
i18n/lang/utils.py