Metadata-Version: 2.1
Name: i18n.lang
Version: 0.0.3
Summary: A module used for building and translating data to create application internationally
Home-page: UNKNOWN
Author: Zenqi
License: MIT
Project-URL: Source, https://github.com/znqi/i18n.lang
Platform: UNKNOWN
Provides-Extra: translator
